Metadata-Version: 2.1
Name: TRAPpy
Version: 6.0.1
Summary: Trace Analysis and Plotting
Home-page: https://github.com/ARM-software/trappy
Author: ARM-TRAPPY
Author-email: trappy@arm.com
License: UNKNOWN
Platform: UNKNOWN
Classifier: Development Status :: 5 - Production/Stable
Classifier: Environment :: Web Environment
Classifier: Environment :: Console
Classifier: License :: OSI Approved :: Apache Software License
Classifier: Operating System :: POSIX :: Linux
Classifier: Programming Language :: Python :: 2.7
Classifier: Programming Language :: Python :: 3
Classifier: Topic :: System :: Operating System Kernels :: Linux
Classifier: Topic :: Scientific/Engineering :: Visualization
Requires-Python: >=3.6
Requires-Dist: numpy
Requires-Dist: pyparsing
Requires-Dist: pandas (>=0.15.0)
Requires-Dist: future
Provides-Extra: notebook
Requires-Dist: matplotlib (>=1.3.1) ; extra == 'notebook'
Requires-Dist: ipython (>=3.0.0) ; extra == 'notebook'
Requires-Dist: jupyter (>=1.0.0) ; extra == 'notebook'
